oneNeuron/__all_utils__.py
oneNeuron/__init__.py
oneNeuron/__perceptron__.py
OneNeuron_pypi_Soumyadipta007-0.0.2.dist-info/LICENSE
OneNeuron_pypi_Soumyadipta007-0.0.2.dist-info/METADATA
OneNeuron_pypi_Soumyadipta007-0.0.2.dist-info/WHEEL
OneNeuron_pypi_Soumyadipta007-0.0.2.dist-info/top_level.txt
OneNeuron_pypi_Soumyadipta007-0.0.2.dist-info/RECORD
