Metadata-Version: 2.1
Name: OneNeuron-pypi-Soumyadipta007
Version: 0.0.2
Summary: Implementation of Perceptron
Home-page: https://github.com/Soumyadipta007OneNeuron_pypi
Author: Soumyadipta007
Author-email: soumyadipta0077@gmail.com
License: UNKNOWN
Project-URL: Bug Tracker, https://github.com/{USER_NAME}{PROJECT_NAME}/issues
Platform: UNKNOWN
Classifier: Programming Language :: Python :: 3
Classifier: License :: OSI Approved :: MIT License
Classifier: Operating System :: OS Independent
Requires-Python: >=3.7
License-File: LICENSE
Requires-Dist: numpy
Requires-Dist: tqdm
